MANIFEST.in
README.rst
setup.py
django_shuoshuos.egg-info/PKG-INFO
django_shuoshuos.egg-info/SOURCES.txt
django_shuoshuos.egg-info/dependency_links.txt
django_shuoshuos.egg-info/top_level.txt
shuoshuos/__init__.py
shuoshuos/admin.py
shuoshuos/apps.py
shuoshuos/models.py
shuoshuos/tests.py
shuoshuos/urls.py
shuoshuos/views.py
shuoshuos/migrations/0001_initial.py
shuoshuos/migrations/__init__.py
shuoshuos/static/shuoshuos/style.css
shuoshuos/static/shuoshuos/summer.mp3
shuoshuos/static/shuoshuos/images/bluesee.jpg
shuoshuos/templates/shuoshuos/detail.html
shuoshuos/templates/shuoshuos/index.html